LICENSE
MANIFEST.in
README.rst
setup.py
django_revuo.egg-info/PKG-INFO
django_revuo.egg-info/SOURCES.txt
django_revuo.egg-info/dependency_links.txt
django_revuo.egg-info/requires.txt
django_revuo.egg-info/top_level.txt
revuo/__init__.py
revuo/admin.py
revuo/urls.py
revuo/static/basic-template.css
revuo/static/css/bootstrap-theme.css
revuo/static/css/bootstrap-theme.min.css
revuo/static/css/bootstrap.css
revuo/static/css/bootstrap.min.css
revuo/static/fonts/glyphicons-halflings-regular.eot
revuo/static/fonts/glyphicons-halflings-regular.svg
revuo/static/fonts/glyphicons-halflings-regular.ttf
revuo/static/fonts/glyphicons-halflings-regular.woff
revuo/static/fonts/glyphicons-halflings-regular.woff2
revuo/static/js/bootstrap.js
revuo/static/js/bootstrap.min.js
revuo/templates/registration/login.html
revuo/templates/registration/password_change_done.html
revuo/templates/registration/password_change_form.html
revuo/templates/revuo/B_item.html
revuo/templates/revuo/N_item.html
revuo/templates/revuo/P_item.html
revuo/templates/revuo/base.html
revuo/templates/revuo/blog.html
revuo/templates/revuo/dashboard.html
revuo/templates/revuo/edit_item.html
revuo/templates/revuo/home.html
revuo/templates/revuo/item.html
revuo/templates/revuo/new_item.html
revuo/templates/revuo/news.html
revuo/templates/revuo/publications.html
revuo/templates/revuo/staff.html
revuo/templates/revuo/staff_view.html