Metadata-Version: 1.1
Name: django-revuo
Version: 0.4
Summary: Simple CMS django app
Home-page: https://github.com/Lasanha/revuo
Author: Gabriel Marcondes
Author-email: gabrielgeraldo@gmail.com
License: BSD License
Platform: UNKNOWN
Classifier: Development Status :: 2 - Pre-Alpha
Classifier: Environment :: Web Environment
Classifier: Framework :: Django
Classifier: Intended Audience :: Developers
Classifier: License :: OSI Approved :: BSD License
Classifier: Operating System :: OS Independent
Classifier: Programming Language :: Python
Classifier: Programming Language :: Python :: 3.4
Classifier: Topic :: Internet :: WWW/HTTP
Classifier: Topic :: Internet :: WWW/HTTP :: Dynamic Content
